{
    "total": 599,
    "total_pages": 60,
    "results": [
        {
            "id": "VhzGCc4QauA",
            "created_at": "2017-12-04T09:31:17-05:00",
            "updated_at": "2020-01-14T00:02:05-05:00",
            "promoted_at": null,
            "width": 2304,
            "height": 1536,
            "color": "#110F12",
            "description": "Woke up early to take sunrise Picture in Milan. @aksoysimone was taking some pictures in front of me and it ended up making my picture even more interesting 😁✌️🇮🇹🇮🇹\r\nCheck out more of my shots on https://www.instagram.com/daniilvnoutchkov/",
            "alt_description": "woman wearing red gown facing at cathedral",
            "urls": {
                "raw": "https://images.unsplash.com/photo-1512397739299-fe5a4327d192?ixlib=rb-1.2.1&ixid=eyJhcHBfaWQiOjEwOTk3Nn0",
                "full": "https://images.unsplash.com/photo-1512397739299-fe5a4327d192?ixlib=rb-1.2.1&q=85&fm=jpg&crop=entropy&cs=srgb&ixid=eyJhcHBfaWQiOjEwOTk3Nn0",
                "regular": "https://images.unsplash.com/photo-1512397739299-fe5a4327d192?ixlib=rb-1.2.1&q=80&fm=jpg&crop=entropy&cs=tinysrgb&w=1080&fit=max&ixid=eyJhcHBfaWQiOjEwOTk3Nn0",
                "small": "https://images.unsplash.com/photo-1512397739299-fe5a4327d192?ixlib=rb-1.2.1&q=80&fm=jpg&crop=entropy&cs=tinysrgb&w=400&fit=max&ixid=eyJhcHBfaWQiOjEwOTk3Nn0",
                "thumb": "https://images.unsplash.com/photo-1512397739299-fe5a4327d192?ixlib=rb-1.2.1&q=80&fm=jpg&crop=entropy&cs=tinysrgb&w=200&fit=max&ixid=eyJhcHBfaWQiOjEwOTk3Nn0"
            },
            "links": {
                "self": "https://api.unsplash.com/photos/VhzGCc4QauA",
                "html": "https://unsplash.com/photos/VhzGCc4QauA",
                "download": "https://unsplash.com/photos/VhzGCc4QauA/download",
                "download_location": "https://api.unsplash.com/photos/VhzGCc4QauA/download"
            },
            "categories": [],
            "likes": 97,
            "liked_by_user": false,
            "current_user_collections": [],
            "user": {
                "id": "Y7liAw8mAlM",
                "updated_at": "2020-01-02T12:00:51-05:00",
                "username": "daniilvnoutchkov",
                "name": "Daniil Vnoutchkov",
                "first_name": "Daniil",
                "last_name": "Vnoutchkov",
                "twitter_username": "dvnoutchkov",
                "portfolio_url": "http://www.instagram.com/daniilvnoutchkov/",
                "bio": "Capturing moments all over the world\r\n📬 For business/shooting: daniiltje@gmail.com\r\n🌄Instagram: http://www.instagram.com/daniilvnoutchkov/",
                "location": "London, UK",
                "links": {
                    "self": "https://api.unsplash.com/users/daniilvnoutchkov",
                    "html": "https://unsplash.com/@daniilvnoutchkov",
                    "photos": "https://api.unsplash.com/users/daniilvnoutchkov/photos",
                    "likes": "https://api.unsplash.com/users/daniilvnoutchkov/likes",
                    "portfolio": "https://api.unsplash.com/users/daniilvnoutchkov/portfolio",
                    "following": "https://api.unsplash.com/users/daniilvnoutchkov/following",
                    "followers": "https://api.unsplash.com/users/daniilvnoutchkov/followers"
                },
                "profile_image": {
                    "small": "https://images.unsplash.com/profile-1483779094928-04895548c8aa?ixlib=rb-1.2.1&q=80&fm=jpg&crop=faces&cs=tinysrgb&fit=crop&h=32&w=32",
                    "medium": "https://images.unsplash.com/profile-1483779094928-04895548c8aa?ixlib=rb-1.2.1&q=80&fm=jpg&crop=faces&cs=tinysrgb&fit=crop&h=64&w=64",
                    "large": "https://images.unsplash.com/profile-1483779094928-04895548c8aa?ixlib=rb-1.2.1&q=80&fm=jpg&crop=faces&cs=tinysrgb&fit=crop&h=128&w=128"
                },
                "instagram_username": "daniilvnoutchkov",
                "total_collections": 0,
                "total_likes": 3,
                "total_photos": 32,
                "accepted_tos": true
            },
            "tags": [
                {
                    "type": "search",
                    "title": "human"
                },
                {
                    "type": "landing_page",
                    "title": "person",
                    "source": {
                        "ancestry": {
                            "type": {
                                "slug": "images",
                                "pretty_slug": "Images"
                            },
                            "category": {
                                "slug": "people",
                                "pretty_slug": "People"
                            }
                        },
                        "title": "People Images",
                        "subtitle": "Download free people images",
                        "description": "Choose from a curated selection of people photos. Always free on Unsplash.",
                        "meta_title": "900+ People Images: Download HD Pictures & Photos on Unsplash",
                        "meta_description": "Choose from hundreds of free people photos. Download HD people pictures for free on Unsplash.",
                        "cover_photo": {
                            "id": "RrD8ypt8cjY",
                            "created_at": "2017-07-17T20:10:58-04:00",
                            "updated_at": "2020-01-14T00:02:12-05:00",
                            "promoted_at": "2017-07-19T08:01:02-04:00",
                            "width": 3200,
                            "height": 4800,
                            "color": "#5DC1F1",
                            "description": "Jumping For Joy",
                            "alt_description": "woman wearing white shirt standing",
                            "urls": {
                                "raw": "https://images.unsplash.com/photo-1500336624523-d727130c3328?ixlib=rb-1.2.1",
                                "full": "https://images.unsplash.com/photo-1500336624523-d727130c3328?ixlib=rb-1.2.1&q=85&fm=jpg&crop=entropy&cs=srgb",
                                "regular": "https://images.unsplash.com/photo-1500336624523-d727130c3328?ixlib=rb-1.2.1&q=80&fm=jpg&crop=entropy&cs=tinysrgb&w=1080&fit=max",
                                "small": "https://images.unsplash.com/photo-1500336624523-d727130c3328?ixlib=rb-1.2.1&q=80&fm=jpg&crop=entropy&cs=tinysrgb&w=400&fit=max",
                                "thumb": "https://images.unsplash.com/photo-1500336624523-d727130c3328?ixlib=rb-1.2.1&q=80&fm=jpg&crop=entropy&cs=tinysrgb&w=200&fit=max"
                            },
                            "links": {
                                "self": "https://api.unsplash.com/photos/RrD8ypt8cjY",
                                "html": "https://unsplash.com/photos/RrD8ypt8cjY",
                                "download": "https://unsplash.com/photos/RrD8ypt8cjY/download",
                                "download_location": "https://api.unsplash.com/photos/RrD8ypt8cjY/download"
                            },
                            "categories": [],
                            "likes": 1433,
                            "liked_by_user": false,
                            "current_user_collections": [],
                            "user": {
                                "id": "LKcsJexUCd0",
                                "updated_at": "2020-01-16T02:10:12-05:00",
                                "username": "armedshutter",
                                "name": "Ayo Ogunseinde",
                                "first_name": "Ayo",
                                "last_name": "Ogunseinde",
                                "twitter_username": null,
                                "portfolio_url": "http://www.armedshutter.com",
                                "bio": "feel free to say hi\r\n\r\nig @armedshutter",
                                "location": "Houston",
                                "links": {
                                    "self": "https://api.unsplash.com/users/armedshutter",
                                    "html": "https://unsplash.com/@armedshutter",
                                    "photos": "https://api.unsplash.com/users/armedshutter/photos",
                                    "likes": "https://api.unsplash.com/users/armedshutter/likes",
                                    "portfolio": "https://api.unsplash.com/users/armedshutter/portfolio",
                                    "following": "https://api.unsplash.com/users/armedshutter/following",
                                    "followers": "https://api.unsplash.com/users/armedshutter/followers"
                                },
                                "profile_image": {
                                    "small": "https://images.unsplash.com/profile-fb-1463453058-75f951165e21.jpg?ixlib=rb-1.2.1&q=80&fm=jpg&crop=faces&cs=tinysrgb&fit=crop&h=32&w=32",
                                    "medium": "https://images.unsplash.com/profile-fb-1463453058-75f951165e21.jpg?ixlib=rb-1.2.1&q=80&fm=jpg&crop=faces&cs=tinysrgb&fit=crop&h=64&w=64",
                                    "large": "https://images.unsplash.com/profile-fb-1463453058-75f951165e21.jpg?ixlib=rb-1.2.1&q=80&fm=jpg&crop=faces&cs=tinysrgb&fit=crop&h=128&w=128"
                                },
                                "instagram_username": "armedshutter",
                                "total_collections": 0,
                                "total_likes": 50,
                                "total_photos": 119,
                                "accepted_tos": true
                            }
                        }
                    }
                },
                {
                    "type": "landing_page",
                    "title": "people",
                    "source": {
                        "ancestry": {
                            "type": {
                                "slug": "images",
                                "pretty_slug": "Images"
                            },
                            "category": {
                                "slug": "people",
                                "pretty_slug": "People"
                            }
                        },
                        "title": "People Images",
                        "subtitle": "Download free people images",
                        "description": "Choose from a curated selection of people photos. Always free on Unsplash.",
                        "meta_title": "900+ People Images: Download HD Pictures & Photos on Unsplash",
                        "meta_description": "Choose from hundreds of free people photos. Download HD people pictures for free on Unsplash.",
                        "cover_photo": {
                            "id": "RrD8ypt8cjY",
                            "created_at": "2017-07-17T20:10:58-04:00",
                            "updated_at": "2020-01-14T00:02:12-05:00",
                            "promoted_at": "2017-07-19T08:01:02-04:00",
                            "width": 3200,
                            "height": 4800,
                            "color": "#5DC1F1",
                            "description": "Jumping For Joy",
                            "alt_description": "woman wearing white shirt standing",
                            "urls": {
                                "raw": "https://images.unsplash.com/photo-1500336624523-d727130c3328?ixlib=rb-1.2.1",
                                "full": "https://images.unsplash.com/photo-1500336624523-d727130c3328?ixlib=rb-1.2.1&q=85&fm=jpg&crop=entropy&cs=srgb",
                                "regular": "https://images.unsplash.com/photo-1500336624523-d727130c3328?ixlib=rb-1.2.1&q=80&fm=jpg&crop=entropy&cs=tinysrgb&w=1080&fit=max",
                                "small": "https://images.unsplash.com/photo-1500336624523-d727130c3328?ixlib=rb-1.2.1&q=80&fm=jpg&crop=entropy&cs=tinysrgb&w=400&fit=max",
                                "thumb": "https://images.unsplash.com/photo-1500336624523-d727130c3328?ixlib=rb-1.2.1&q=80&fm=jpg&crop=entropy&cs=tinysrgb&w=200&fit=max"
                            },
                            "links": {
                                "self": "https://api.unsplash.com/photos/RrD8ypt8cjY",
                                "html": "https://unsplash.com/photos/RrD8ypt8cjY",
                                "download": "https://unsplash.com/photos/RrD8ypt8cjY/download",
                                "download_location": "https://api.unsplash.com/photos/RrD8ypt8cjY/download"
                            },
                            "categories": [],
                            "likes": 1433,
                            "liked_by_user": false,
                            "current_user_collections": [],
                            "user": {
                                "id": "LKcsJexUCd0",
                                "updated_at": "2020-01-16T02:10:12-05:00",
                                "username": "armedshutter",
                                "name": "Ayo Ogunseinde",
                                "first_name": "Ayo",
                                "last_name": "Ogunseinde",
                                "twitter_username": null,
                                "portfolio_url": "http://www.armedshutter.com",
                                "bio": "feel free to say hi\r\n\r\nig @armedshutter",
                                "location": "Houston",
                                "links": {
                                    "self": "https://api.unsplash.com/users/armedshutter",
                                    "html": "https://unsplash.com/@armedshutter",
                                    "photos": "https://api.unsplash.com/users/armedshutter/photos",
                                    "likes": "https://api.unsplash.com/users/armedshutter/likes",
                                    "portfolio": "https://api.unsplash.com/users/armedshutter/portfolio",
                                    "following": "https://api.unsplash.com/users/armedshutter/following",
                                    "followers": "https://api.unsplash.com/users/armedshutter/followers"
                                },
                                "profile_image": {
                                    "small": "https://images.unsplash.com/profile-fb-1463453058-75f951165e21.jpg?ixlib=rb-1.2.1&q=80&fm=jpg&crop=faces&cs=tinysrgb&fit=crop&h=32&w=32",
                                    "medium": "https://images.unsplash.com/profile-fb-1463453058-75f951165e21.jpg?ixlib=rb-1.2.1&q=80&fm=jpg&crop=faces&cs=tinysrgb&fit=crop&h=64&w=64",
                                    "large": "https://images.unsplash.com/profile-fb-1463453058-75f951165e21.jpg?ixlib=rb-1.2.1&q=80&fm=jpg&crop=faces&cs=tinysrgb&fit=crop&h=128&w=128"
                                },
                                "instagram_username": "armedshutter",
                                "total_collections": 0,
                                "total_likes": 50,
                                "total_photos": 119,
                                "accepted_tos": true
                            }
                        }
                    }
                }
            ]
        },
        {
            "id": "xEQLO9EGu64",
            "created_at": "2018-03-07T11:32:22-05:00",
            "updated_at": "2020-01-21T00:04:23-05:00",
            "promoted_at": null,
            "width": 2812,
            "height": 3750,
            "color": "#0A0A0B",
            "description": null,
            "alt_description": "Milan Cathedral",
            "urls": {
                "raw": "https://images.unsplash.com/photo-1520440229-6469a149ac59?ixlib=rb-1.2.1&ixid=eyJhcHBfaWQiOjEwOTk3Nn0",
                "full": "https://images.unsplash.com/photo-1520440229-6469a149ac59?ixlib=rb-1.2.1&q=85&fm=jpg&crop=entropy&cs=srgb&ixid=eyJhcHBfaWQiOjEwOTk3Nn0",
                "regular": "https://images.unsplash.com/photo-1520440229-6469a149ac59?ixlib=rb-1.2.1&q=80&fm=jpg&crop=entropy&cs=tinysrgb&w=1080&fit=max&ixid=eyJhcHBfaWQiOjEwOTk3Nn0",
                "small": "https://images.unsplash.com/photo-1520440229-6469a149ac59?ixlib=rb-1.2.1&q=80&fm=jpg&crop=entropy&cs=tinysrgb&w=400&fit=max&ixid=eyJhcHBfaWQiOjEwOTk3Nn0",
                "thumb": "https://images.unsplash.com/photo-1520440229-6469a149ac59?ixlib=rb-1.2.1&q=80&fm=jpg&crop=entropy&cs=tinysrgb&w=200&fit=max&ixid=eyJhcHBfaWQiOjEwOTk3Nn0"
            },
            "links": {
                "self": "https://api.unsplash.com/photos/xEQLO9EGu64",
                "html": "https://unsplash.com/photos/xEQLO9EGu64",
                "download": "https://unsplash.com/photos/xEQLO9EGu64/download",
                "download_location": "https://api.unsplash.com/photos/xEQLO9EGu64/download"
            },
            "categories": [],
            "likes": 183,
            "liked_by_user": false,
            "current_user_collections": [],
            "user": {
                "id": "F3xsq0YApHk",
                "updated_at": "2020-01-11T20:50:09-05:00",
                "username": "yoitscalebb",
                "name": "Caleb Stokes",
                "first_name": "Caleb",
                "last_name": "Stokes",
                "twitter_username": null,
                "portfolio_url": "https://www.paypal.me/kleb997",
                "bio": "Amateur photographer, trying to make it big someday. ",
                "location": null,
                "links": {
                    "self": "https://api.unsplash.com/users/yoitscalebb",
                    "html": "https://unsplash.com/@yoitscalebb",
                    "photos": "https://api.unsplash.com/users/yoitscalebb/photos",
                    "likes": "https://api.unsplash.com/users/yoitscalebb/likes",
                    "portfolio": "https://api.unsplash.com/users/yoitscalebb/portfolio",
                    "following": "https://api.unsplash.com/users/yoitscalebb/following",
                    "followers": "https://api.unsplash.com/users/yoitscalebb/followers"
                },
                "profile_image": {
                    "small": "https://images.unsplash.com/profile-1543376719749-1d99a5988b3c?ixlib=rb-1.2.1&q=80&fm=jpg&crop=faces&cs=tinysrgb&fit=crop&h=32&w=32",
                    "medium": "https://images.unsplash.com/profile-1543376719749-1d99a5988b3c?ixlib=rb-1.2.1&q=80&fm=jpg&crop=faces&cs=tinysrgb&fit=crop&h=64&w=64",
                    "large": "https://images.unsplash.com/profile-1543376719749-1d99a5988b3c?ixlib=rb-1.2.1&q=80&fm=jpg&crop=faces&cs=tinysrgb&fit=crop&h=128&w=128"
                },
                "instagram_username": "C_pics_97",
                "total_collections": 0,
                "total_likes": 20,
                "total_photos": 67,
                "accepted_tos": true
            },
            "tags": [
                {
                    "type": "landing_page",
                    "title": "person",
                    "source": {
                        "ancestry": {
                            "type": {
                                "slug": "images",
                                "pretty_slug": "Images"
                            },
                            "category": {
                                "slug": "people",
                                "pretty_slug": "People"
                            }
                        },
                        "title": "People Images",
                        "subtitle": "Download free people images",
                        "description": "Choose from a curated selection of people photos. Always free on Unsplash.",
                        "meta_title": "900+ People Images: Download HD Pictures & Photos on Unsplash",
                        "meta_description": "Choose from hundreds of free people photos. Download HD people pictures for free on Unsplash.",
                        "cover_photo": {
                            "id": "RrD8ypt8cjY",
                            "created_at": "2017-07-17T20:10:58-04:00",
                            "updated_at": "2020-01-14T00:02:12-05:00",
                            "promoted_at": "2017-07-19T08:01:02-04:00",
                            "width": 3200,
                            "height": 4800,
                            "color": "#5DC1F1",
                            "description": "Jumping For Joy",
                            "alt_description": "woman wearing white shirt standing",
                            "urls": {
                                "raw": "https://images.unsplash.com/photo-1500336624523-d727130c3328?ixlib=rb-1.2.1",
                                "full": "https://images.unsplash.com/photo-1500336624523-d727130c3328?ixlib=rb-1.2.1&q=85&fm=jpg&crop=entropy&cs=srgb",
                                "regular": "https://images.unsplash.com/photo-1500336624523-d727130c3328?ixlib=rb-1.2.1&q=80&fm=jpg&crop=entropy&cs=tinysrgb&w=1080&fit=max",
                                "small": "https://images.unsplash.com/photo-1500336624523-d727130c3328?ixlib=rb-1.2.1&q=80&fm=jpg&crop=entropy&cs=tinysrgb&w=400&fit=max",
                                "thumb": "https://images.unsplash.com/photo-1500336624523-d727130c3328?ixlib=rb-1.2.1&q=80&fm=jpg&crop=entropy&cs=tinysrgb&w=200&fit=max"
                            },
                            "links": {
                                "self": "https://api.unsplash.com/photos/RrD8ypt8cjY",
                                "html": "https://unsplash.com/photos/RrD8ypt8cjY",
                                "download": "https://unsplash.com/photos/RrD8ypt8cjY/download",
                                "download_location": "https://api.unsplash.com/photos/RrD8ypt8cjY/download"
                            },
                            "categories": [],
                            "likes": 1433,
                            "liked_by_user": false,
                            "current_user_collections": [],
                            "user": {
                                "id": "LKcsJexUCd0",
                                "updated_at": "2020-01-16T02:10:12-05:00",
                                "username": "armedshutter",
                                "name": "Ayo Ogunseinde",
                                "first_name": "Ayo",
                                "last_name": "Ogunseinde",
                                "twitter_username": null,
                                "portfolio_url": "http://www.armedshutter.com",
                                "bio": "feel free to say hi\r\n\r\nig @armedshutter",
                                "location": "Houston",
                                "links": {
                                    "self": "https://api.unsplash.com/users/armedshutter",
                                    "html": "https://unsplash.com/@armedshutter",
                                    "photos": "https://api.unsplash.com/users/armedshutter/photos",
                                    "likes": "https://api.unsplash.com/users/armedshutter/likes",
                                    "portfolio": "https://api.unsplash.com/users/armedshutter/portfolio",
                                    "following": "https://api.unsplash.com/users/armedshutter/following",
                                    "followers": "https://api.unsplash.com/users/armedshutter/followers"
                                },
                                "profile_image": {
                                    "small": "https://images.unsplash.com/profile-fb-1463453058-75f951165e21.jpg?ixlib=rb-1.2.1&q=80&fm=jpg&crop=faces&cs=tinysrgb&fit=crop&h=32&w=32",
                                    "medium": "https://images.unsplash.com/profile-fb-1463453058-75f951165e21.jpg?ixlib=rb-1.2.1&q=80&fm=jpg&crop=faces&cs=tinysrgb&fit=crop&h=64&w=64",
                                    "large": "https://images.unsplash.com/profile-fb-1463453058-75f951165e21.jpg?ixlib=rb-1.2.1&q=80&fm=jpg&crop=faces&cs=tinysrgb&fit=crop&h=128&w=128"
                                },
                                "instagram_username": "armedshutter",
                                "total_collections": 0,
                                "total_likes": 50,
                                "total_photos": 119,
                                "accepted_tos": true
                            }
                        }
                    }
                },
                {
                    "type": "landing_page",
                    "title": "people",
                    "source": {
                        "ancestry": {
                            "type": {
                                "slug": "images",
                                "pretty_slug": "Images"
                            },
                            "category": {
                                "slug": "people",
                                "pretty_slug": "People"
                            }
                        },
                        "title": "People Images",
                        "subtitle": "Download free people images",
                        "description": "Choose from a curated selection of people photos. Always free on Unsplash.",
                        "meta_title": "900+ People Images: Download HD Pictures & Photos on Unsplash",
                        "meta_description": "Choose from hundreds of free people photos. Download HD people pictures for free on Unsplash.",
                        "cover_photo": {
                            "id": "RrD8ypt8cjY",
                            "created_at": "2017-07-17T20:10:58-04:00",
                            "updated_at": "2020-01-14T00:02:12-05:00",
                            "promoted_at": "2017-07-19T08:01:02-04:00",
                            "width": 3200,
                            "height": 4800,
                            "color": "#5DC1F1",
                            "description": "Jumping For Joy",
                            "alt_description": "woman wearing white shirt standing",
                            "urls": {
                                "raw": "https://images.unsplash.com/photo-1500336624523-d727130c3328?ixlib=rb-1.2.1",
                                "full": "https://images.unsplash.com/photo-1500336624523-d727130c3328?ixlib=rb-1.2.1&q=85&fm=jpg&crop=entropy&cs=srgb",
                                "regular": "https://images.unsplash.com/photo-1500336624523-d727130c3328?ixlib=rb-1.2.1&q=80&fm=jpg&crop=entropy&cs=tinysrgb&w=1080&fit=max",
                                "small": "https://images.unsplash.com/photo-1500336624523-d727130c3328?ixlib=rb-1.2.1&q=80&fm=jpg&crop=entropy&cs=tinysrgb&w=400&fit=max",
                                "thumb": "https://images.unsplash.com/photo-1500336624523-d727130c3328?ixlib=rb-1.2.1&q=80&fm=jpg&crop=entropy&cs=tinysrgb&w=200&fit=max"
                            },
                            "links": {
                                "self": "https://api.unsplash.com/photos/RrD8ypt8cjY",
                                "html": "https://unsplash.com/photos/RrD8ypt8cjY",
                                "download": "https://unsplash.com/photos/RrD8ypt8cjY/download",
                                "download_location": "https://api.unsplash.com/photos/RrD8ypt8cjY/download"
                            },
                            "categories": [],
                            "likes": 1433,
                            "liked_by_user": false,
                            "current_user_collections": [],
                            "user": {
                                "id": "LKcsJexUCd0",
                                "updated_at": "2020-01-16T02:10:12-05:00",
                                "username": "armedshutter",
                                "name": "Ayo Ogunseinde",
                                "first_name": "Ayo",
                                "last_name": "Ogunseinde",
                                "twitter_username": null,
                                "portfolio_url": "http://www.armedshutter.com",
                                "bio": "feel free to say hi\r\n\r\nig @armedshutter",
                                "location": "Houston",
                                "links": {
                                    "self": "https://api.unsplash.com/users/armedshutter",
                                    "html": "https://unsplash.com/@armedshutter",
                                    "photos": "https://api.unsplash.com/users/armedshutter/photos",
                                    "likes": "https://api.unsplash.com/users/armedshutter/likes",
                                    "portfolio": "https://api.unsplash.com/users/armedshutter/portfolio",
                                    "following": "https://api.unsplash.com/users/armedshutter/following",
                                    "followers": "https://api.unsplash.com/users/armedshutter/followers"
                                },
                                "profile_image": {
                                    "small": "https://images.unsplash.com/profile-fb-1463453058-75f951165e21.jpg?ixlib=rb-1.2.1&q=80&fm=jpg&crop=faces&cs=tinysrgb&fit=crop&h=32&w=32",
                                    "medium": "https://images.unsplash.com/profile-fb-1463453058-75f951165e21.jpg?ixlib=rb-1.2.1&q=80&fm=jpg&crop=faces&cs=tinysrgb&fit=crop&h=64&w=64",
                                    "large": "https://images.unsplash.com/profile-fb-1463453058-75f951165e21.jpg?ixlib=rb-1.2.1&q=80&fm=jpg&crop=faces&cs=tinysrgb&fit=crop&h=128&w=128"
                                },
                                "instagram_username": "armedshutter",
                                "total_collections": 0,
                                "total_likes": 50,
                                "total_photos": 119,
                                "accepted_tos": true
                            }
                        }
                    }
                },
                {
                    "type": "landing_page",
                    "title": "italy",
                    "source": {
                        "ancestry": {
                            "type": {
                                "slug": "images",
                                "pretty_slug": "Images"
                            },
                            "category": {
                                "slug": "travel",
                                "pretty_slug": "Travel"
                            },
                            "subcategory": {
                                "slug": "italy",
                                "pretty_slug": "Italy"
                            }
                        },
                        "title": "Italy Images",
                        "subtitle": "Download free Italy images",
                        "description": "Choose from a curated selection of Italy photos. Always free on Unsplash.",
                        "meta_title": "900+ Italy Images: Download HD Pictures & Photos on Unsplash",
                        "meta_description": "Choose from hundreds of free Italy photos. Download HD Italy pictures for free on Unsplash.",
                        "cover_photo": {
                            "id": "rknrvCrfS1k",
                            "created_at": "2018-01-20T16:28:57-05:00",
                            "updated_at": "2019-12-28T00:05:33-05:00",
                            "promoted_at": "2018-01-21T07:32:39-05:00",
                            "width": 2675,
                            "height": 4027,
                            "color": "#EBF2F5",
                            "description": "The Cliffs of Cinque Terre",
                            "alt_description": "Manarola, Italy",
                            "urls": {
                                "raw": "https://images.unsplash.com/photo-1516483638261-f4dbaf036963?ixlib=rb-1.2.1&ixid=eyJhcHBfaWQiOjExMDk0fQ",
                                "full": "https://images.unsplash.com/photo-1516483638261-f4dbaf036963?ixlib=rb-1.2.1&q=85&fm=jpg&crop=entropy&cs=srgb&ixid=eyJhcHBfaWQiOjExMDk0fQ",
                                "regular": "https://images.unsplash.com/photo-1516483638261-f4dbaf036963?ixlib=rb-1.2.1&q=80&fm=jpg&crop=entropy&cs=tinysrgb&w=1080&fit=max&ixid=eyJhcHBfaWQiOjExMDk0fQ",
                                "small": "https://images.unsplash.com/photo-1516483638261-f4dbaf036963?ixlib=rb-1.2.1&q=80&fm=jpg&crop=entropy&cs=tinysrgb&w=400&fit=max&ixid=eyJhcHBfaWQiOjExMDk0fQ",
                                "thumb": "https://images.unsplash.com/photo-1516483638261-f4dbaf036963?ixlib=rb-1.2.1&q=80&fm=jpg&crop=entropy&cs=tinysrgb&w=200&fit=max&ixid=eyJhcHBfaWQiOjExMDk0fQ"
                            },
                            "links": {
                                "self": "https://api.unsplash.com/photos/rknrvCrfS1k",
                                "html": "https://unsplash.com/photos/rknrvCrfS1k",
                                "download": "https://unsplash.com/photos/rknrvCrfS1k/download",
                                "download_location": "https://api.unsplash.com/photos/rknrvCrfS1k/download"
                            },
                            "categories": [],
                            "likes": 637,
                            "liked_by_user": false,
                            "current_user_collections": [],
                            "user": {
                                "id": "NuPaOVVjvqA",
                                "updated_at": "2019-12-29T04:04:04-05:00",
                                "username": "jackward",
                                "name": "Jack Ward",
                                "first_name": "Jack",
                                "last_name": "Ward",
                                "twitter_username": "jwardu",
                                "portfolio_url": null,
                                "bio": "Adventure/Landscape Photographer",
                                "location": "Boston, Ma",
                                "links": {
                                    "self": "https://api.unsplash.com/users/jackward",
                                    "html": "https://unsplash.com/@jackward",
                                    "photos": "https://api.unsplash.com/users/jackward/photos",
                                    "likes": "https://api.unsplash.com/users/jackward/likes",
                                    "portfolio": "https://api.unsplash.com/users/jackward/portfolio",
                                    "following": "https://api.unsplash.com/users/jackward/following",
                                    "followers": "https://api.unsplash.com/users/jackward/followers"
                                },
                                "profile_image": {
                                    "small": "https://images.unsplash.com/profile-1522420435626-e26c29024ea9?ixlib=rb-1.2.1&q=80&fm=jpg&crop=faces&cs=tinysrgb&fit=crop&h=32&w=32",
                                    "medium": "https://images.unsplash.com/profile-1522420435626-e26c29024ea9?ixlib=rb-1.2.1&q=80&fm=jpg&crop=faces&cs=tinysrgb&fit=crop&h=64&w=64",
                                    "large": "https://images.unsplash.com/profile-1522420435626-e26c29024ea9?ixlib=rb-1.2.1&q=80&fm=jpg&crop=faces&cs=tinysrgb&fit=crop&h=128&w=128"
                                },
                                "instagram_username": "jwardu",
                                "total_collections": 1,
                                "total_likes": 901,
                                "total_photos": 192,
                                "accepted_tos": true
                            }
                        }
                    }
                }
            ]
        },
        {
            "id": "JhjDL3TZKJk",
            "created_at": "2018-01-18T12:25:29-05:00",
            "updated_at": "2020-01-21T00:04:32-05:00",
            "promoted_at": "2018-01-19T09:45:47-05:00",
            "width": 3385,
            "height": 2536,
            "color": "#F9C9AF",
            "description": null,
            "alt_description": "brown cathedral",
            "urls": {
                "raw": "https://images.unsplash.com/photo-1516296270211-f3ae5494e65d?ixlib=rb-1.2.1&ixid=eyJhcHBfaWQiOjEwOTk3Nn0",
                "full": "https://images.unsplash.com/photo-1516296270211-f3ae5494e65d?ixlib=rb-1.2.1&q=85&fm=jpg&crop=entropy&cs=srgb&ixid=eyJhcHBfaWQiOjEwOTk3Nn0",
                "regular": "https://images.unsplash.com/photo-1516296270211-f3ae5494e65d?ixlib=rb-1.2.1&q=80&fm=jpg&crop=entropy&cs=tinysrgb&w=1080&fit=max&ixid=eyJhcHBfaWQiOjEwOTk3Nn0",
                "small": "https://images.unsplash.com/photo-1516296270211-f3ae5494e65d?ixlib=rb-1.2.1&q=80&fm=jpg&crop=entropy&cs=tinysrgb&w=400&fit=max&ixid=eyJhcHBfaWQiOjEwOTk3Nn0",
                "thumb": "https://images.unsplash.com/photo-1516296270211-f3ae5494e65d?ixlib=rb-1.2.1&q=80&fm=jpg&crop=entropy&cs=tinysrgb&w=200&fit=max&ixid=eyJhcHBfaWQiOjEwOTk3Nn0"
            },
            "links": {
                "self": "https://api.unsplash.com/photos/JhjDL3TZKJk",
                "html": "https://unsplash.com/photos/JhjDL3TZKJk",
                "download": "https://unsplash.com/photos/JhjDL3TZKJk/download",
                "download_location": "https://api.unsplash.com/photos/JhjDL3TZKJk/download"
            },
            "categories": [],
            "likes": 383,
            "liked_by_user": false,
            "current_user_collections": [],
            "user": {
                "id": "7rhBmzxHi-0",
                "updated_at": "2020-01-19T08:58:45-05:00",
                "username": "vorosbenisop",
                "name": "Benjamin Voros",
                "first_name": "Benjamin",
                "last_name": "Voros",
                "twitter_username": "voros_benjamin",
                "portfolio_url": "http://www.vorosbenjamin.com",
                "bio": null,
                "location": "Hungary",
                "links": {
                    "self": "https://api.unsplash.com/users/vorosbenisop",
                    "html": "https://unsplash.com/@vorosbenisop",
                    "photos": "https://api.unsplash.com/users/vorosbenisop/photos",
                    "likes": "https://api.unsplash.com/users/vorosbenisop/likes",
                    "portfolio": "https://api.unsplash.com/users/vorosbenisop/portfolio",
                    "following": "https://api.unsplash.com/users/vorosbenisop/following",
                    "followers": "https://api.unsplash.com/users/vorosbenisop/followers"
                },
                "profile_image": {
                    "small": "https://images.unsplash.com/profile-1501580705195-e3eda67a7256?ixlib=rb-1.2.1&q=80&fm=jpg&crop=faces&cs=tinysrgb&fit=crop&h=32&w=32",
                    "medium": "https://images.unsplash.com/profile-1501580705195-e3eda67a7256?ixlib=rb-1.2.1&q=80&fm=jpg&crop=faces&cs=tinysrgb&fit=crop&h=64&w=64",
                    "large": "https://images.unsplash.com/profile-1501580705195-e3eda67a7256?ixlib=rb-1.2.1&q=80&fm=jpg&crop=faces&cs=tinysrgb&fit=crop&h=128&w=128"
                },
                "instagram_username": "voros_beni",
                "total_collections": 0,
                "total_likes": 897,
                "total_photos": 102,
                "accepted_tos": true
            },
            "tags": [
                {
                    "type": "search",
                    "title": "cathedral"
                },
                {
                    "type": "search",
                    "title": "building"
                },
                {
                    "type": "search",
                    "title": "architecture"
                }
            ]
        },
        {
            "id": "Gdu4YDNxo10",
            "created_at": "2017-12-02T12:36:58-05:00",
            "updated_at": "2019-12-21T00:06:38-05:00",
            "promoted_at": null,
            "width": 5184,
            "height": 3456,
            "color": "#130F0A",
            "description": "Golden hour in Milan.",
            "alt_description": "brown and blue concrete buildings",
            "urls": {
                "raw": "https://images.unsplash.com/photo-1512236077335-f1cda9239c11?ixlib=rb-1.2.1&ixid=eyJhcHBfaWQiOjEwOTk3Nn0",
                "full": "https://images.unsplash.com/photo-1512236077335-f1cda9239c11?ixlib=rb-1.2.1&q=85&fm=jpg&crop=entropy&cs=srgb&ixid=eyJhcHBfaWQiOjEwOTk3Nn0",
                "regular": "https://images.unsplash.com/photo-1512236077335-f1cda9239c11?ixlib=rb-1.2.1&q=80&fm=jpg&crop=entropy&cs=tinysrgb&w=1080&fit=max&ixid=eyJhcHBfaWQiOjEwOTk3Nn0",
                "small": "https://images.unsplash.com/photo-1512236077335-f1cda9239c11?ixlib=rb-1.2.1&q=80&fm=jpg&crop=entropy&cs=tinysrgb&w=400&fit=max&ixid=eyJhcHBfaWQiOjEwOTk3Nn0",
                "thumb": "https://images.unsplash.com/photo-1512236077335-f1cda9239c11?ixlib=rb-1.2.1&q=80&fm=jpg&crop=entropy&cs=tinysrgb&w=200&fit=max&ixid=eyJhcHBfaWQiOjEwOTk3Nn0"
            },
            "links": {
                "self": "https://api.unsplash.com/photos/Gdu4YDNxo10",
                "html": "https://unsplash.com/photos/Gdu4YDNxo10",
                "download": "https://unsplash.com/photos/Gdu4YDNxo10/download",
                "download_location": "https://api.unsplash.com/photos/Gdu4YDNxo10/download"
            },
            "categories": [],
            "likes": 70,
            "liked_by_user": false,
            "current_user_collections": [],
            "user": {
                "id": "QbJ8M01fcCY",
                "updated_at": "2019-11-30T08:44:22-05:00",
                "username": "mettrm",
                "name": "Matteo Raimondi",
                "first_name": "Matteo",
                "last_name": "Raimondi",
                "twitter_username": null,
                "portfolio_url": "https://www.behance.net/teo92r1089b9",
                "bio": "Italian Designer",
                "location": null,
                "links": {
                    "self": "https://api.unsplash.com/users/mettrm",
                    "html": "https://unsplash.com/@mettrm",
                    "photos": "https://api.unsplash.com/users/mettrm/photos",
                    "likes": "https://api.unsplash.com/users/mettrm/likes",
                    "portfolio": "https://api.unsplash.com/users/mettrm/portfolio",
                    "following": "https://api.unsplash.com/users/mettrm/following",
                    "followers": "https://api.unsplash.com/users/mettrm/followers"
                },
                "profile_image": {
                    "small": "https://images.unsplash.com/profile-1512162159978-a534dbf31edd?ixlib=rb-1.2.1&q=80&fm=jpg&crop=faces&cs=tinysrgb&fit=crop&h=32&w=32",
                    "medium": "https://images.unsplash.com/profile-1512162159978-a534dbf31edd?ixlib=rb-1.2.1&q=80&fm=jpg&crop=faces&cs=tinysrgb&fit=crop&h=64&w=64",
                    "large": "https://images.unsplash.com/profile-1512162159978-a534dbf31edd?ixlib=rb-1.2.1&q=80&fm=jpg&crop=faces&cs=tinysrgb&fit=crop&h=128&w=128"
                },
                "instagram_username": "Mettrm",
                "total_collections": 0,
                "total_likes": 72,
                "total_photos": 6,
                "accepted_tos": false
            },
            "tags": [
                {
                    "type": "landing_page",
                    "title": "italy",
                    "source": {
                        "ancestry": {
                            "type": {
                                "slug": "images",
                                "pretty_slug": "Images"
                            },
                            "category": {
                                "slug": "travel",
                                "pretty_slug": "Travel"
                            },
                            "subcategory": {
                                "slug": "italy",
                                "pretty_slug": "Italy"
                            }
                        },
                        "title": "Italy Images",
                        "subtitle": "Download free Italy images",
                        "description": "Choose from a curated selection of Italy photos. Always free on Unsplash.",
                        "meta_title": "900+ Italy Images: Download HD Pictures & Photos on Unsplash",
                        "meta_description": "Choose from hundreds of free Italy photos. Download HD Italy pictures for free on Unsplash.",
                        "cover_photo": {
                            "id": "rknrvCrfS1k",
                            "created_at": "2018-01-20T16:28:57-05:00",
                            "updated_at": "2019-12-28T00:05:33-05:00",
                            "promoted_at": "2018-01-21T07:32:39-05:00",
                            "width": 2675,
                            "height": 4027,
                            "color": "#EBF2F5",
                            "description": "The Cliffs of Cinque Terre",
                            "alt_description": "Manarola, Italy",
                            "urls": {
                                "raw": "https://images.unsplash.com/photo-1516483638261-f4dbaf036963?ixlib=rb-1.2.1&ixid=eyJhcHBfaWQiOjExMDk0fQ",
                                "full": "https://images.unsplash.com/photo-1516483638261-f4dbaf036963?ixlib=rb-1.2.1&q=85&fm=jpg&crop=entropy&cs=srgb&ixid=eyJhcHBfaWQiOjExMDk0fQ",
                                "regular": "https://images.unsplash.com/photo-1516483638261-f4dbaf036963?ixlib=rb-1.2.1&q=80&fm=jpg&crop=entropy&cs=tinysrgb&w=1080&fit=max&ixid=eyJhcHBfaWQiOjExMDk0fQ",
                                "small": "https://images.unsplash.com/photo-1516483638261-f4dbaf036963?ixlib=rb-1.2.1&q=80&fm=jpg&crop=entropy&cs=tinysrgb&w=400&fit=max&ixid=eyJhcHBfaWQiOjExMDk0fQ",
                                "thumb": "https://images.unsplash.com/photo-1516483638261-f4dbaf036963?ixlib=rb-1.2.1&q=80&fm=jpg&crop=entropy&cs=tinysrgb&w=200&fit=max&ixid=eyJhcHBfaWQiOjExMDk0fQ"
                            },
                            "links": {
                                "self": "https://api.unsplash.com/photos/rknrvCrfS1k",
                                "html": "https://unsplash.com/photos/rknrvCrfS1k",
                                "download": "https://unsplash.com/photos/rknrvCrfS1k/download",
                                "download_location": "https://api.unsplash.com/photos/rknrvCrfS1k/download"
                            },
                            "categories": [],
                            "likes": 637,
                            "liked_by_user": false,
                            "current_user_collections": [],
                            "user": {
                                "id": "NuPaOVVjvqA",
                                "updated_at": "2019-12-29T04:04:04-05:00",
                                "username": "jackward",
                                "name": "Jack Ward",
                                "first_name": "Jack",
                                "last_name": "Ward",
                                "twitter_username": "jwardu",
                                "portfolio_url": null,
                                "bio": "Adventure/Landscape Photographer",
                                "location": "Boston, Ma",
                                "links": {
                                    "self": "https://api.unsplash.com/users/jackward",
                                    "html": "https://unsplash.com/@jackward",
                                    "photos": "https://api.unsplash.com/users/jackward/photos",
                                    "likes": "https://api.unsplash.com/users/jackward/likes",
                                    "portfolio": "https://api.unsplash.com/users/jackward/portfolio",
                                    "following": "https://api.unsplash.com/users/jackward/following",
                                    "followers": "https://api.unsplash.com/users/jackward/followers"
                                },
                                "profile_image": {
                                    "small": "https://images.unsplash.com/profile-1522420435626-e26c29024ea9?ixlib=rb-1.2.1&q=80&fm=jpg&crop=faces&cs=tinysrgb&fit=crop&h=32&w=32",
                                    "medium": "https://images.unsplash.com/profile-1522420435626-e26c29024ea9?ixlib=rb-1.2.1&q=80&fm=jpg&crop=faces&cs=tinysrgb&fit=crop&h=64&w=64",
                                    "large": "https://images.unsplash.com/profile-1522420435626-e26c29024ea9?ixlib=rb-1.2.1&q=80&fm=jpg&crop=faces&cs=tinysrgb&fit=crop&h=128&w=128"
                                },
                                "instagram_username": "jwardu",
                                "total_collections": 1,
                                "total_likes": 901,
                                "total_photos": 192,
                                "accepted_tos": true
                            }
                        }
                    }
                },
                {
                    "type": "search",
                    "title": "building"
                },
                {
                    "type": "search",
                    "title": "tower"
                }
            ]
        },
        {
            "id": "-YzMZYqwoH4",
            "created_at": "2017-12-18T02:14:08-05:00",
            "updated_at": "2020-01-21T00:03:04-05:00",
            "promoted_at": "2017-12-18T10:19:34-05:00",
            "width": 4896,
            "height": 3264,
            "color": "#F5EED7",
            "description": "Christmas lights",
            "alt_description": "reflective photography of string lights above river",
            "urls": {
                "raw": "https://images.unsplash.com/photo-1513581166391-887a96ddeafd?ixlib=rb-1.2.1&ixid=eyJhcHBfaWQiOjEwOTk3Nn0",
                "full": "https://images.unsplash.com/photo-1513581166391-887a96ddeafd?ixlib=rb-1.2.1&q=85&fm=jpg&crop=entropy&cs=srgb&ixid=eyJhcHBfaWQiOjEwOTk3Nn0",
                "regular": "https://images.unsplash.com/photo-1513581166391-887a96ddeafd?ixlib=rb-1.2.1&q=80&fm=jpg&crop=entropy&cs=tinysrgb&w=1080&fit=max&ixid=eyJhcHBfaWQiOjEwOTk3Nn0",
                "small": "https://images.unsplash.com/photo-1513581166391-887a96ddeafd?ixlib=rb-1.2.1&q=80&fm=jpg&crop=entropy&cs=tinysrgb&w=400&fit=max&ixid=eyJhcHBfaWQiOjEwOTk3Nn0",
                "thumb": "https://images.unsplash.com/photo-1513581166391-887a96ddeafd?ixlib=rb-1.2.1&q=80&fm=jpg&crop=entropy&cs=tinysrgb&w=200&fit=max&ixid=eyJhcHBfaWQiOjEwOTk3Nn0"
            },
            "links": {
                "self": "https://api.unsplash.com/photos/-YzMZYqwoH4",
                "html": "https://unsplash.com/photos/-YzMZYqwoH4",
                "download": "https://unsplash.com/photos/-YzMZYqwoH4/download",
                "download_location": "https://api.unsplash.com/photos/-YzMZYqwoH4/download"
            },
            "categories": [],
            "likes": 633,
            "liked_by_user": false,
            "current_user_collections": [],
            "user": {
                "id": "VeIm9BP-du0",
                "updated_at": "2020-01-21T09:44:26-05:00",
                "username": "cristina_gottardi",
                "name": "Cristina Gottardi",
                "first_name": "Cristina",
                "last_name": "Gottardi",
                "twitter_username": null,
                "portfolio_url": "https://www.instagram.com/cristinagottardi/",
                "bio": "Hi! I’m an enthusiastic 26 year old Graphic & Web Designer living and working in Milan.\r\nI'm from Trentino - in northern Italy - and I'm in love with the silence of landscapes and views hidden by my beloved mountains.\r\n\r\n",
                "location": "Trento, North Italy",
                "links": {
                    "self": "https://api.unsplash.com/users/cristina_gottardi",
                    "html": "https://unsplash.com/@cristina_gottardi",
                    "photos": "https://api.unsplash.com/users/cristina_gottardi/photos",
                    "likes": "https://api.unsplash.com/users/cristina_gottardi/likes",
                    "portfolio": "https://api.unsplash.com/users/cristina_gottardi/portfolio",
                    "following": "https://api.unsplash.com/users/cristina_gottardi/following",
                    "followers": "https://api.unsplash.com/users/cristina_gottardi/followers"
                },
                "profile_image": {
                    "small": "https://images.unsplash.com/profile-1509140709644-5b9d6cd408f9?ixlib=rb-1.2.1&q=80&fm=jpg&crop=faces&cs=tinysrgb&fit=crop&h=32&w=32",
                    "medium": "https://images.unsplash.com/profile-1509140709644-5b9d6cd408f9?ixlib=rb-1.2.1&q=80&fm=jpg&crop=faces&cs=tinysrgb&fit=crop&h=64&w=64",
                    "large": "https://images.unsplash.com/profile-1509140709644-5b9d6cd408f9?ixlib=rb-1.2.1&q=80&fm=jpg&crop=faces&cs=tinysrgb&fit=crop&h=128&w=128"
                },
                "instagram_username": "cristina.gottardi",
                "total_collections": 0,
                "total_likes": 286,
                "total_photos": 269,
                "accepted_tos": true
            },
            "tags": [
                {
                    "type": "landing_page",
                    "title": "italy",
                    "source": {
                        "ancestry": {
                            "type": {
                                "slug": "images",
                                "pretty_slug": "Images"
                            },
                            "category": {
                                "slug": "travel",
                                "pretty_slug": "Travel"
                            },
                            "subcategory": {
                                "slug": "italy",
                                "pretty_slug": "Italy"
                            }
                        },
                        "title": "Italy Images",
                        "subtitle": "Download free Italy images",
                        "description": "Choose from a curated selection of Italy photos. Always free on Unsplash.",
                        "meta_title": "900+ Italy Images: Download HD Pictures & Photos on Unsplash",
                        "meta_description": "Choose from hundreds of free Italy photos. Download HD Italy pictures for free on Unsplash.",
                        "cover_photo": {
                            "id": "rknrvCrfS1k",
                            "created_at": "2018-01-20T16:28:57-05:00",
                            "updated_at": "2019-12-28T00:05:33-05:00",
                            "promoted_at": "2018-01-21T07:32:39-05:00",
                            "width": 2675,
                            "height": 4027,
                            "color": "#EBF2F5",
                            "description": "The Cliffs of Cinque Terre",
                            "alt_description": "Manarola, Italy",
                            "urls": {
                                "raw": "https://images.unsplash.com/photo-1516483638261-f4dbaf036963?ixlib=rb-1.2.1&ixid=eyJhcHBfaWQiOjExMDk0fQ",
                                "full": "https://images.unsplash.com/photo-1516483638261-f4dbaf036963?ixlib=rb-1.2.1&q=85&fm=jpg&crop=entropy&cs=srgb&ixid=eyJhcHBfaWQiOjExMDk0fQ",
                                "regular": "https://images.unsplash.com/photo-1516483638261-f4dbaf036963?ixlib=rb-1.2.1&q=80&fm=jpg&crop=entropy&cs=tinysrgb&w=1080&fit=max&ixid=eyJhcHBfaWQiOjExMDk0fQ",
                                "small": "https://images.unsplash.com/photo-1516483638261-f4dbaf036963?ixlib=rb-1.2.1&q=80&fm=jpg&crop=entropy&cs=tinysrgb&w=400&fit=max&ixid=eyJhcHBfaWQiOjExMDk0fQ",
                                "thumb": "https://images.unsplash.com/photo-1516483638261-f4dbaf036963?ixlib=rb-1.2.1&q=80&fm=jpg&crop=entropy&cs=tinysrgb&w=200&fit=max&ixid=eyJhcHBfaWQiOjExMDk0fQ"
                            },
                            "links": {
                                "self": "https://api.unsplash.com/photos/rknrvCrfS1k",
                                "html": "https://unsplash.com/photos/rknrvCrfS1k",
                                "download": "https://unsplash.com/photos/rknrvCrfS1k/download",
                                "download_location": "https://api.unsplash.com/photos/rknrvCrfS1k/download"
                            },
                            "categories": [],
                            "likes": 637,
                            "liked_by_user": false,
                            "current_user_collections": [],
                            "user": {
                                "id": "NuPaOVVjvqA",
                                "updated_at": "2019-12-29T04:04:04-05:00",
                                "username": "jackward",
                                "name": "Jack Ward",
                                "first_name": "Jack",
                                "last_name": "Ward",
                                "twitter_username": "jwardu",
                                "portfolio_url": null,
                                "bio": "Adventure/Landscape Photographer",
                                "location": "Boston, Ma",
                                "links": {
                                    "self": "https://api.unsplash.com/users/jackward",
                                    "html": "https://unsplash.com/@jackward",
                                    "photos": "https://api.unsplash.com/users/jackward/photos",
                                    "likes": "https://api.unsplash.com/users/jackward/likes",
                                    "portfolio": "https://api.unsplash.com/users/jackward/portfolio",
                                    "following": "https://api.unsplash.com/users/jackward/following",
                                    "followers": "https://api.unsplash.com/users/jackward/followers"
                                },
                                "profile_image": {
                                    "small": "https://images.unsplash.com/profile-1522420435626-e26c29024ea9?ixlib=rb-1.2.1&q=80&fm=jpg&crop=faces&cs=tinysrgb&fit=crop&h=32&w=32",
                                    "medium": "https://images.unsplash.com/profile-1522420435626-e26c29024ea9?ixlib=rb-1.2.1&q=80&fm=jpg&crop=faces&cs=tinysrgb&fit=crop&h=64&w=64",
                                    "large": "https://images.unsplash.com/profile-1522420435626-e26c29024ea9?ixlib=rb-1.2.1&q=80&fm=jpg&crop=faces&cs=tinysrgb&fit=crop&h=128&w=128"
                                },
                                "instagram_username": "jwardu",
                                "total_collections": 1,
                                "total_likes": 901,
                                "total_photos": 192,
                                "accepted_tos": true
                            }
                        }
                    }
                },
                {
                    "type": "search",
                    "title": "milano"
                },
                {
                    "type": "search",
                    "title": "urban"
                }
            ]
        },
        {
            "id": "ZXfL1btjbsU",
            "created_at": "2018-01-07T07:45:24-05:00",
            "updated_at": "2020-01-21T00:03:57-05:00",
            "promoted_at": null,
            "width": 6000,
            "height": 3376,
            "color": "#05080B",
            "description": "Check out my instagram account for more photos, @ac.almelor",
            "alt_description": "man standing in front of concrete structures",
            "urls": {
                "raw": "https://images.unsplash.com/photo-1515329060981-428a461b46df?ixlib=rb-1.2.1&ixid=eyJhcHBfaWQiOjEwOTk3Nn0",
                "full": "https://images.unsplash.com/photo-1515329060981-428a461b46df?ixlib=rb-1.2.1&q=85&fm=jpg&crop=entropy&cs=srgb&ixid=eyJhcHBfaWQiOjEwOTk3Nn0",
                "regular": "https://images.unsplash.com/photo-1515329060981-428a461b46df?ixlib=rb-1.2.1&q=80&fm=jpg&crop=entropy&cs=tinysrgb&w=1080&fit=max&ixid=eyJhcHBfaWQiOjEwOTk3Nn0",
                "small": "https://images.unsplash.com/photo-1515329060981-428a461b46df?ixlib=rb-1.2.1&q=80&fm=jpg&crop=entropy&cs=tinysrgb&w=400&fit=max&ixid=eyJhcHBfaWQiOjEwOTk3Nn0",
                "thumb": "https://images.unsplash.com/photo-1515329060981-428a461b46df?ixlib=rb-1.2.1&q=80&fm=jpg&crop=entropy&cs=tinysrgb&w=200&fit=max&ixid=eyJhcHBfaWQiOjEwOTk3Nn0"
            },
            "links": {
                "self": "https://api.unsplash.com/photos/ZXfL1btjbsU",
                "html": "https://unsplash.com/photos/ZXfL1btjbsU",
                "download": "https://unsplash.com/photos/ZXfL1btjbsU/download",
                "download_location": "https://api.unsplash.com/photos/ZXfL1btjbsU/download"
            },
            "categories": [],
            "likes": 38,
            "liked_by_user": false,
            "current_user_collections": [],
            "user": {
                "id": "aOwRlCYjask",
                "updated_at": "2020-01-16T03:05:30-05:00",
                "username": "acalmelor",
                "name": "AC Almelor",
                "first_name": "AC",
                "last_name": "Almelor",
                "twitter_username": null,
                "portfolio_url": null,
                "bio": "Check out my instagram account for more photos, @ac.almelor",
                "location": "Berlin, Germany",
                "links": {
                    "self": "https://api.unsplash.com/users/acalmelor",
                    "html": "https://unsplash.com/@acalmelor",
                    "photos": "https://api.unsplash.com/users/acalmelor/photos",
                    "likes": "https://api.unsplash.com/users/acalmelor/likes",
                    "portfolio": "https://api.unsplash.com/users/acalmelor/portfolio",
                    "following": "https://api.unsplash.com/users/acalmelor/following",
                    "followers": "https://api.unsplash.com/users/acalmelor/followers"
                },
                "profile_image": {
                    "small": "https://images.unsplash.com/profile-1511450536532-d730450cb547?ixlib=rb-1.2.1&q=80&fm=jpg&crop=faces&cs=tinysrgb&fit=crop&h=32&w=32",
                    "medium": "https://images.unsplash.com/profile-1511450536532-d730450cb547?ixlib=rb-1.2.1&q=80&fm=jpg&crop=faces&cs=tinysrgb&fit=crop&h=64&w=64",
                    "large": "https://images.unsplash.com/profile-1511450536532-d730450cb547?ixlib=rb-1.2.1&q=80&fm=jpg&crop=faces&cs=tinysrgb&fit=crop&h=128&w=128"
                },
                "instagram_username": "ac.almelor",
                "total_collections": 0,
                "total_likes": 0,
                "total_photos": 42,
                "accepted_tos": true
            },
            "tags": [
                {
                    "type": "search",
                    "title": "architecture"
                },
                {
                    "type": "search",
                    "title": "urban"
                },
                {
                    "type": "landing_page",
                    "title": "city",
                    "source": {
                        "ancestry": {
                            "type": {
                                "slug": "wallpapers",
                                "pretty_slug": "HD Wallpapers"
                            },
                            "category": {
                                "slug": "travel",
                                "pretty_slug": "Travel"
                            },
                            "subcategory": {
                                "slug": "city",
                                "pretty_slug": "City"
                            }
                        },
                        "title": "HD City Wallpapers",
                        "subtitle": "Download Free City Wallpapers",
                        "description": "Choose from a curated selection of city wallpapers for your mobile and desktop screens. Always free on Unsplash.",
                        "meta_title": "City Wallpapers: Free HD Download [500+ HQ] | Unsplash",
                        "meta_description": "Choose from hundreds of free city wallpapers. Download HD wallpapers for free on Unsplash.",
                        "cover_photo": {
                            "id": "wpU4veNGnHg",
                            "created_at": "2016-12-02T16:36:41-05:00",
                            "updated_at": "2019-12-21T00:02:22-05:00",
                            "promoted_at": "2016-12-02T16:36:41-05:00",
                            "width": 5472,
                            "height": 3648,
                            "color": "#0D0C0D",
                            "description": "7am shot",
                            "alt_description": "high rise buildings city scape photography",
                            "urls": {
                                "raw": "https://images.unsplash.com/photo-1480714378408-67cf0d13bc1b?ixlib=rb-1.2.1",
                                "full": "https://images.unsplash.com/photo-1480714378408-67cf0d13bc1b?ixlib=rb-1.2.1&q=85&fm=jpg&crop=entropy&cs=srgb",
                                "regular": "https://images.unsplash.com/photo-1480714378408-67cf0d13bc1b?ixlib=rb-1.2.1&q=80&fm=jpg&crop=entropy&cs=tinysrgb&w=1080&fit=max",
                                "small": "https://images.unsplash.com/photo-1480714378408-67cf0d13bc1b?ixlib=rb-1.2.1&q=80&fm=jpg&crop=entropy&cs=tinysrgb&w=400&fit=max",
                                "thumb": "https://images.unsplash.com/photo-1480714378408-67cf0d13bc1b?ixlib=rb-1.2.1&q=80&fm=jpg&crop=entropy&cs=tinysrgb&w=200&fit=max"
                            },
                            "links": {
                                "self": "https://api.unsplash.com/photos/wpU4veNGnHg",
                                "html": "https://unsplash.com/photos/wpU4veNGnHg",
                                "download": "https://unsplash.com/photos/wpU4veNGnHg/download",
                                "download_location": "https://api.unsplash.com/photos/wpU4veNGnHg/download"
                            },
                            "categories": [],
                            "likes": 871,
                            "liked_by_user": false,
                            "current_user_collections": [],
                            "user": {
                                "id": "DE2lKLbSMug",
                                "updated_at": "2019-12-20T14:03:00-05:00",
                                "username": "benobro",
                                "name": "ben o'bro",
                                "first_name": "ben",
                                "last_name": "o'bro",
                                "twitter_username": null,
                                "portfolio_url": "http://www.benobro.com",
                                "bio": null,
                                "location": "GVA",
                                "links": {
                                    "self": "https://api.unsplash.com/users/benobro",
                                    "html": "https://unsplash.com/@benobro",
                                    "photos": "https://api.unsplash.com/users/benobro/photos",
                                    "likes": "https://api.unsplash.com/users/benobro/likes",
                                    "portfolio": "https://api.unsplash.com/users/benobro/portfolio",
                                    "following": "https://api.unsplash.com/users/benobro/following",
                                    "followers": "https://api.unsplash.com/users/benobro/followers"
                                },
                                "profile_image": {
                                    "small": "https://images.unsplash.com/profile-1515016860295-94be36a36d1d?ixlib=rb-1.2.1&q=80&fm=jpg&crop=faces&cs=tinysrgb&fit=crop&h=32&w=32",
                                    "medium": "https://images.unsplash.com/profile-1515016860295-94be36a36d1d?ixlib=rb-1.2.1&q=80&fm=jpg&crop=faces&cs=tinysrgb&fit=crop&h=64&w=64",
                                    "large": "https://images.unsplash.com/profile-1515016860295-94be36a36d1d?ixlib=rb-1.2.1&q=80&fm=jpg&crop=faces&cs=tinysrgb&fit=crop&h=128&w=128"
                                },
                                "instagram_username": "benobro",
                                "total_collections": 0,
                                "total_likes": 64,
                                "total_photos": 15,
                                "accepted_tos": true
                            }
                        }
                    }
                }
            ]
        },
        {
            "id": "g35Frf_NfU0",
            "created_at": "2018-10-09T14:18:44-04:00",
            "updated_at": "2020-01-14T00:02:04-05:00",
            "promoted_at": null,
            "width": 3591,
            "height": 4489,
            "color": "#FAFCFC",
            "description": "THE EYE OF MILANO",
            "alt_description": "low angle photo of stain glass cathedral",
            "urls": {
                "raw": "https://images.unsplash.com/photo-1539108842340-ae72fbf39857?ixlib=rb-1.2.1&ixid=eyJhcHBfaWQiOjEwOTk3Nn0",
                "full": "https://images.unsplash.com/photo-1539108842340-ae72fbf39857?ixlib=rb-1.2.1&q=85&fm=jpg&crop=entropy&cs=srgb&ixid=eyJhcHBfaWQiOjEwOTk3Nn0",
                "regular": "https://images.unsplash.com/photo-1539108842340-ae72fbf39857?ixlib=rb-1.2.1&q=80&fm=jpg&crop=entropy&cs=tinysrgb&w=1080&fit=max&ixid=eyJhcHBfaWQiOjEwOTk3Nn0",
                "small": "https://images.unsplash.com/photo-1539108842340-ae72fbf39857?ixlib=rb-1.2.1&q=80&fm=jpg&crop=entropy&cs=tinysrgb&w=400&fit=max&ixid=eyJhcHBfaWQiOjEwOTk3Nn0",
                "thumb": "https://images.unsplash.com/photo-1539108842340-ae72fbf39857?ixlib=rb-1.2.1&q=80&fm=jpg&crop=entropy&cs=tinysrgb&w=200&fit=max&ixid=eyJhcHBfaWQiOjEwOTk3Nn0"
            },
            "links": {
                "self": "https://api.unsplash.com/photos/g35Frf_NfU0",
                "html": "https://unsplash.com/photos/g35Frf_NfU0",
                "download": "https://unsplash.com/photos/g35Frf_NfU0/download",
                "download_location": "https://api.unsplash.com/photos/g35Frf_NfU0/download"
            },
            "categories": [],
            "likes": 75,
            "liked_by_user": false,
            "current_user_collections": [],
            "user": {
                "id": "q0h40eNQ45Q",
                "updated_at": "2019-11-30T14:35:44-05:00",
                "username": "partissimo",
                "name": "ARNO PARTISSIMO",
                "first_name": "ARNO",
                "last_name": "PARTISSIMO",
                "twitter_username": "Partissimo",
                "portfolio_url": "https://instagram.com/arnopartissimo",
                "bio": "ENJOY !! \r\n\r\nINSTAGRAM : arnopartissimo",
                "location": null,
                "links": {
                    "self": "https://api.unsplash.com/users/partissimo",
                    "html": "https://unsplash.com/@partissimo",
                    "photos": "https://api.unsplash.com/users/partissimo/photos",
                    "likes": "https://api.unsplash.com/users/partissimo/likes",
                    "portfolio": "https://api.unsplash.com/users/partissimo/portfolio",
                    "following": "https://api.unsplash.com/users/partissimo/following",
                    "followers": "https://api.unsplash.com/users/partissimo/followers"
                },
                "profile_image": {
                    "small": "https://images.unsplash.com/profile-1527198610622-f2dfa6334cce?ixlib=rb-1.2.1&q=80&fm=jpg&crop=faces&cs=tinysrgb&fit=crop&h=32&w=32",
                    "medium": "https://images.unsplash.com/profile-1527198610622-f2dfa6334cce?ixlib=rb-1.2.1&q=80&fm=jpg&crop=faces&cs=tinysrgb&fit=crop&h=64&w=64",
                    "large": "https://images.unsplash.com/profile-1527198610622-f2dfa6334cce?ixlib=rb-1.2.1&q=80&fm=jpg&crop=faces&cs=tinysrgb&fit=crop&h=128&w=128"
                },
                "instagram_username": "Arnopartissimo",
                "total_collections": 0,
                "total_likes": 4,
                "total_photos": 8,
                "accepted_tos": true
            },
            "tags": [
                {
                    "type": "search",
                    "title": "building"
                },
                {
                    "type": "search",
                    "title": "architecture"
                },
                {
                    "type": "landing_page",
                    "title": "window",
                    "source": {
                        "ancestry": {
                            "type": {
                                "slug": "wallpapers",
                                "pretty_slug": "HD Wallpapers"
                            },
                            "category": {
                                "slug": "desktop",
                                "pretty_slug": "Desktop"
                            },
                            "subcategory": {
                                "slug": "windows",
                                "pretty_slug": "Windows"
                            }
                        },
                        "title": "HD Windows Wallpapers",
                        "subtitle": "Download Free Windows Wallpapers",
                        "description": "Choose from a curated selection of Windows wallpapers for your mobile and desktop screens. Always free on Unsplash.",
                        "meta_title": "Windows Wallpapers: Free HD Download [500+ HQ] | Unsplash",
                        "meta_description": "Choose from hundreds of free Windows wallpapers. Download HD wallpapers for free on Unsplash.",
                        "cover_photo": {
                            "id": "dClHqW-EfS8",
                            "created_at": "2017-11-22T22:04:37-05:00",
                            "updated_at": "2020-01-14T00:04:11-05:00",
                            "promoted_at": "2017-11-23T10:03:25-05:00",
                            "width": 5472,
                            "height": 3648,
                            "color": "#1C1C1C",
                            "description": "DDP",
                            "alt_description": "structural shot of building",
                            "urls": {
                                "raw": "https://images.unsplash.com/photo-1511406239133-2c1130a2d754?ixlib=rb-1.2.1",
                                "full": "https://images.unsplash.com/photo-1511406239133-2c1130a2d754?ixlib=rb-1.2.1&q=85&fm=jpg&crop=entropy&cs=srgb",
                                "regular": "https://images.unsplash.com/photo-1511406239133-2c1130a2d754?ixlib=rb-1.2.1&q=80&fm=jpg&crop=entropy&cs=tinysrgb&w=1080&fit=max",
                                "small": "https://images.unsplash.com/photo-1511406239133-2c1130a2d754?ixlib=rb-1.2.1&q=80&fm=jpg&crop=entropy&cs=tinysrgb&w=400&fit=max",
                                "thumb": "https://images.unsplash.com/photo-1511406239133-2c1130a2d754?ixlib=rb-1.2.1&q=80&fm=jpg&crop=entropy&cs=tinysrgb&w=200&fit=max"
                            },
                            "links": {
                                "self": "https://api.unsplash.com/photos/dClHqW-EfS8",
                                "html": "https://unsplash.com/photos/dClHqW-EfS8",
                                "download": "https://unsplash.com/photos/dClHqW-EfS8/download",
                                "download_location": "https://api.unsplash.com/photos/dClHqW-EfS8/download"
                            },
                            "categories": [],
                            "likes": 93,
                            "liked_by_user": false,
                            "current_user_collections": [],
                            "user": {
                                "id": "mA08QQzQf8Y",
                                "updated_at": "2020-01-18T04:28:02-05:00",
                                "username": "charlesdeluvio",
                                "name": "Charles",
                                "first_name": "Charles",
                                "last_name": null,
                                "twitter_username": "charlesdeluvio",
                                "portfolio_url": "http://charlesdeluvio.com",
                                "bio": "Designer at Unsplash. 🇵🇭",
                                "location": "Montreal",
                                "links": {
                                    "self": "https://api.unsplash.com/users/charlesdeluvio",
                                    "html": "https://unsplash.com/@charlesdeluvio",
                                    "photos": "https://api.unsplash.com/users/charlesdeluvio/photos",
                                    "likes": "https://api.unsplash.com/users/charlesdeluvio/likes",
                                    "portfolio": "https://api.unsplash.com/users/charlesdeluvio/portfolio",
                                    "following": "https://api.unsplash.com/users/charlesdeluvio/following",
                                    "followers": "https://api.unsplash.com/users/charlesdeluvio/followers"
                                },
                                "profile_image": {
                                    "small": "https://images.unsplash.com/profile-1515694660956-9133b2f53e3b?ixlib=rb-1.2.1&q=80&fm=jpg&crop=faces&cs=tinysrgb&fit=crop&h=32&w=32",
                                    "medium": "https://images.unsplash.com/profile-1515694660956-9133b2f53e3b?ixlib=rb-1.2.1&q=80&fm=jpg&crop=faces&cs=tinysrgb&fit=crop&h=64&w=64",
                                    "large": "https://images.unsplash.com/profile-1515694660956-9133b2f53e3b?ixlib=rb-1.2.1&q=80&fm=jpg&crop=faces&cs=tinysrgb&fit=crop&h=128&w=128"
                                },
                                "instagram_username": null,
                                "total_collections": 128,
                                "total_likes": 4260,
                                "total_photos": 495,
                                "accepted_tos": true
                            }
                        }
                    }
                }
            ]
        },
        {
            "id": "hQPZTxt34RQ",
            "created_at": "2018-02-16T11:20:29-05:00",
            "updated_at": "2020-01-21T00:04:48-05:00",
            "promoted_at": "2018-02-18T12:49:16-05:00",
            "width": 1713,
            "height": 2141,
            "color": "#0C0F10",
            "description": "I had a about 30 minutes to explore Milan and had seen pictures of this place in the past.  I knew that the entire place was massive, so I packed up the 8mm and decided to try shooting ultra wide to capture all of it’s beauty.",
            "alt_description": "people standing inside building",
            "urls": {
                "raw": "https://images.unsplash.com/photo-1518797814703-ed31ee241ef8?ixlib=rb-1.2.1&ixid=eyJhcHBfaWQiOjEwOTk3Nn0",
                "full": "https://images.unsplash.com/photo-1518797814703-ed31ee241ef8?ixlib=rb-1.2.1&q=85&fm=jpg&crop=entropy&cs=srgb&ixid=eyJhcHBfaWQiOjEwOTk3Nn0",
                "regular": "https://images.unsplash.com/photo-1518797814703-ed31ee241ef8?ixlib=rb-1.2.1&q=80&fm=jpg&crop=entropy&cs=tinysrgb&w=1080&fit=max&ixid=eyJhcHBfaWQiOjEwOTk3Nn0",
                "small": "https://images.unsplash.com/photo-1518797814703-ed31ee241ef8?ixlib=rb-1.2.1&q=80&fm=jpg&crop=entropy&cs=tinysrgb&w=400&fit=max&ixid=eyJhcHBfaWQiOjEwOTk3Nn0",
                "thumb": "https://images.unsplash.com/photo-1518797814703-ed31ee241ef8?ixlib=rb-1.2.1&q=80&fm=jpg&crop=entropy&cs=tinysrgb&w=200&fit=max&ixid=eyJhcHBfaWQiOjEwOTk3Nn0"
            },
            "links": {
                "self": "https://api.unsplash.com/photos/hQPZTxt34RQ",
                "html": "https://unsplash.com/photos/hQPZTxt34RQ",
                "download": "https://unsplash.com/photos/hQPZTxt34RQ/download",
                "download_location": "https://api.unsplash.com/photos/hQPZTxt34RQ/download"
            },
            "categories": [],
            "likes": 199,
            "liked_by_user": false,
            "current_user_collections": [],
            "user": {
                "id": "VA1NcZYRHxs",
                "updated_at": "2019-11-30T10:01:10-05:00",
                "username": "jordanpulmano",
                "name": "Jordan Pulmano",
                "first_name": "Jordan",
                "last_name": "Pulmano",
                "twitter_username": "JordanPulmano",
                "portfolio_url": null,
                "bio": "Cinematographer & Photographer based in Central California.",
                "location": "Fresno, Ca",
                "links": {
                    "self": "https://api.unsplash.com/users/jordanpulmano",
                    "html": "https://unsplash.com/@jordanpulmano",
                    "photos": "https://api.unsplash.com/users/jordanpulmano/photos",
                    "likes": "https://api.unsplash.com/users/jordanpulmano/likes",
                    "portfolio": "https://api.unsplash.com/users/jordanpulmano/portfolio",
                    "following": "https://api.unsplash.com/users/jordanpulmano/following",
                    "followers": "https://api.unsplash.com/users/jordanpulmano/followers"
                },
                "profile_image": {
                    "small": "https://images.unsplash.com/profile-1573490250226-5b182ea5aa31image?ixlib=rb-1.2.1&q=80&fm=jpg&crop=faces&cs=tinysrgb&fit=crop&h=32&w=32",
                    "medium": "https://images.unsplash.com/profile-1573490250226-5b182ea5aa31image?ixlib=rb-1.2.1&q=80&fm=jpg&crop=faces&cs=tinysrgb&fit=crop&h=64&w=64",
                    "large": "https://images.unsplash.com/profile-1573490250226-5b182ea5aa31image?ixlib=rb-1.2.1&q=80&fm=jpg&crop=faces&cs=tinysrgb&fit=crop&h=128&w=128"
                },
                "instagram_username": "jordanpulmano",
                "total_collections": 0,
                "total_likes": 0,
                "total_photos": 12,
                "accepted_tos": true
            },
            "tags": [
                {
                    "type": "landing_page",
                    "title": "italy",
                    "source": {
                        "ancestry": {
                            "type": {
                                "slug": "images",
                                "pretty_slug": "Images"
                            },
                            "category": {
                                "slug": "travel",
                                "pretty_slug": "Travel"
                            },
                            "subcategory": {
                                "slug": "italy",
                                "pretty_slug": "Italy"
                            }
                        },
                        "title": "Italy Images",
                        "subtitle": "Download free Italy images",
                        "description": "Choose from a curated selection of Italy photos. Always free on Unsplash.",
                        "meta_title": "900+ Italy Images: Download HD Pictures & Photos on Unsplash",
                        "meta_description": "Choose from hundreds of free Italy photos. Download HD Italy pictures for free on Unsplash.",
                        "cover_photo": {
                            "id": "rknrvCrfS1k",
                            "created_at": "2018-01-20T16:28:57-05:00",
                            "updated_at": "2019-12-28T00:05:33-05:00",
                            "promoted_at": "2018-01-21T07:32:39-05:00",
                            "width": 2675,
                            "height": 4027,
                            "color": "#EBF2F5",
                            "description": "The Cliffs of Cinque Terre",
                            "alt_description": "Manarola, Italy",
                            "urls": {
                                "raw": "https://images.unsplash.com/photo-1516483638261-f4dbaf036963?ixlib=rb-1.2.1&ixid=eyJhcHBfaWQiOjExMDk0fQ",
                                "full": "https://images.unsplash.com/photo-1516483638261-f4dbaf036963?ixlib=rb-1.2.1&q=85&fm=jpg&crop=entropy&cs=srgb&ixid=eyJhcHBfaWQiOjExMDk0fQ",
                                "regular": "https://images.unsplash.com/photo-1516483638261-f4dbaf036963?ixlib=rb-1.2.1&q=80&fm=jpg&crop=entropy&cs=tinysrgb&w=1080&fit=max&ixid=eyJhcHBfaWQiOjExMDk0fQ",
                                "small": "https://images.unsplash.com/photo-1516483638261-f4dbaf036963?ixlib=rb-1.2.1&q=80&fm=jpg&crop=entropy&cs=tinysrgb&w=400&fit=max&ixid=eyJhcHBfaWQiOjExMDk0fQ",
                                "thumb": "https://images.unsplash.com/photo-1516483638261-f4dbaf036963?ixlib=rb-1.2.1&q=80&fm=jpg&crop=entropy&cs=tinysrgb&w=200&fit=max&ixid=eyJhcHBfaWQiOjExMDk0fQ"
                            },
                            "links": {
                                "self": "https://api.unsplash.com/photos/rknrvCrfS1k",
                                "html": "https://unsplash.com/photos/rknrvCrfS1k",
                                "download": "https://unsplash.com/photos/rknrvCrfS1k/download",
                                "download_location": "https://api.unsplash.com/photos/rknrvCrfS1k/download"
                            },
                            "categories": [],
                            "likes": 637,
                            "liked_by_user": false,
                            "current_user_collections": [],
                            "user": {
                                "id": "NuPaOVVjvqA",
                                "updated_at": "2019-12-29T04:04:04-05:00",
                                "username": "jackward",
                                "name": "Jack Ward",
                                "first_name": "Jack",
                                "last_name": "Ward",
                                "twitter_username": "jwardu",
                                "portfolio_url": null,
                                "bio": "Adventure/Landscape Photographer",
                                "location": "Boston, Ma",
                                "links": {
                                    "self": "https://api.unsplash.com/users/jackward",
                                    "html": "https://unsplash.com/@jackward",
                                    "photos": "https://api.unsplash.com/users/jackward/photos",
                                    "likes": "https://api.unsplash.com/users/jackward/likes",
                                    "portfolio": "https://api.unsplash.com/users/jackward/portfolio",
                                    "following": "https://api.unsplash.com/users/jackward/following",
                                    "followers": "https://api.unsplash.com/users/jackward/followers"
                                },
                                "profile_image": {
                                    "small": "https://images.unsplash.com/profile-1522420435626-e26c29024ea9?ixlib=rb-1.2.1&q=80&fm=jpg&crop=faces&cs=tinysrgb&fit=crop&h=32&w=32",
                                    "medium": "https://images.unsplash.com/profile-1522420435626-e26c29024ea9?ixlib=rb-1.2.1&q=80&fm=jpg&crop=faces&cs=tinysrgb&fit=crop&h=64&w=64",
                                    "large": "https://images.unsplash.com/profile-1522420435626-e26c29024ea9?ixlib=rb-1.2.1&q=80&fm=jpg&crop=faces&cs=tinysrgb&fit=crop&h=128&w=128"
                                },
                                "instagram_username": "jwardu",
                                "total_collections": 1,
                                "total_likes": 901,
                                "total_photos": 192,
                                "accepted_tos": true
                            }
                        }
                    }
                },
                {
                    "type": "search",
                    "title": "architecture"
                },
                {
                    "type": "search",
                    "title": "milan"
                }
            ]
        },
        {
            "id": "UdLVYEbElMI",
            "created_at": "2018-06-22T18:50:24-04:00",
            "updated_at": "2020-01-14T00:05:07-05:00",
            "promoted_at": null,
            "width": 4407,
            "height": 4224,
            "color": "#040606",
            "description": null,
            "alt_description": "selective focus photography of white concrete building under white sky",
            "urls": {
                "raw": "https://images.unsplash.com/photo-1529707768959-ac4a3407e8c6?ixlib=rb-1.2.1&ixid=eyJhcHBfaWQiOjEwOTk3Nn0",
                "full": "https://images.unsplash.com/photo-1529707768959-ac4a3407e8c6?ixlib=rb-1.2.1&q=85&fm=jpg&crop=entropy&cs=srgb&ixid=eyJhcHBfaWQiOjEwOTk3Nn0",
                "regular": "https://images.unsplash.com/photo-1529707768959-ac4a3407e8c6?ixlib=rb-1.2.1&q=80&fm=jpg&crop=entropy&cs=tinysrgb&w=1080&fit=max&ixid=eyJhcHBfaWQiOjEwOTk3Nn0",
                "small": "https://images.unsplash.com/photo-1529707768959-ac4a3407e8c6?ixlib=rb-1.2.1&q=80&fm=jpg&crop=entropy&cs=tinysrgb&w=400&fit=max&ixid=eyJhcHBfaWQiOjEwOTk3Nn0",
                "thumb": "https://images.unsplash.com/photo-1529707768959-ac4a3407e8c6?ixlib=rb-1.2.1&q=80&fm=jpg&crop=entropy&cs=tinysrgb&w=200&fit=max&ixid=eyJhcHBfaWQiOjEwOTk3Nn0"
            },
            "links": {
                "self": "https://api.unsplash.com/photos/UdLVYEbElMI",
                "html": "https://unsplash.com/photos/UdLVYEbElMI",
                "download": "https://unsplash.com/photos/UdLVYEbElMI/download",
                "download_location": "https://api.unsplash.com/photos/UdLVYEbElMI/download"
            },
            "categories": [],
            "likes": 28,
            "liked_by_user": false,
            "current_user_collections": [],
            "user": {
                "id": "Vx_6OvsC3Qw",
                "updated_at": "2019-11-30T10:45:42-05:00",
                "username": "thoots",
                "name": "Manu B",
                "first_name": "Manu",
                "last_name": "B",
                "twitter_username": null,
                "portfolio_url": null,
                "bio": null,
                "location": null,
                "links": {
                    "self": "https://api.unsplash.com/users/thoots",
                    "html": "https://unsplash.com/@thoots",
                    "photos": "https://api.unsplash.com/users/thoots/photos",
                    "likes": "https://api.unsplash.com/users/thoots/likes",
                    "portfolio": "https://api.unsplash.com/users/thoots/portfolio",
                    "following": "https://api.unsplash.com/users/thoots/following",
                    "followers": "https://api.unsplash.com/users/thoots/followers"
                },
                "profile_image": {
                    "small": "https://images.unsplash.com/profile-fb-1517875343-f8ad9cab953c.jpg?ixlib=rb-1.2.1&q=80&fm=jpg&crop=faces&cs=tinysrgb&fit=crop&h=32&w=32",
                    "medium": "https://images.unsplash.com/profile-fb-1517875343-f8ad9cab953c.jpg?ixlib=rb-1.2.1&q=80&fm=jpg&crop=faces&cs=tinysrgb&fit=crop&h=64&w=64",
                    "large": "https://images.unsplash.com/profile-fb-1517875343-f8ad9cab953c.jpg?ixlib=rb-1.2.1&q=80&fm=jpg&crop=faces&cs=tinysrgb&fit=crop&h=128&w=128"
                },
                "instagram_username": null,
                "total_collections": 0,
                "total_likes": 0,
                "total_photos": 38,
                "accepted_tos": true
            },
            "tags": [
                {
                    "type": "search",
                    "title": "building"
                },
                {
                    "type": "search",
                    "title": "architecture"
                },
                {
                    "type": "search",
                    "title": "church"
                }
            ]
        },
        {
            "id": "Bm4IvGf2al0",
            "created_at": "2018-11-06T09:25:23-05:00",
            "updated_at": "2019-12-21T00:06:38-05:00",
            "promoted_at": null,
            "width": 4272,
            "height": 2848,
            "color": "#050705",
            "description": null,
            "alt_description": "low-angle view of building during daytime",
            "urls": {
                "raw": "https://images.unsplash.com/photo-1541514254856-8caa32916423?ixlib=rb-1.2.1&ixid=eyJhcHBfaWQiOjEwOTk3Nn0",
                "full": "https://images.unsplash.com/photo-1541514254856-8caa32916423?ixlib=rb-1.2.1&q=85&fm=jpg&crop=entropy&cs=srgb&ixid=eyJhcHBfaWQiOjEwOTk3Nn0",
                "regular": "https://images.unsplash.com/photo-1541514254856-8caa32916423?ixlib=rb-1.2.1&q=80&fm=jpg&crop=entropy&cs=tinysrgb&w=1080&fit=max&ixid=eyJhcHBfaWQiOjEwOTk3Nn0",
                "small": "https://images.unsplash.com/photo-1541514254856-8caa32916423?ixlib=rb-1.2.1&q=80&fm=jpg&crop=entropy&cs=tinysrgb&w=400&fit=max&ixid=eyJhcHBfaWQiOjEwOTk3Nn0",
                "thumb": "https://images.unsplash.com/photo-1541514254856-8caa32916423?ixlib=rb-1.2.1&q=80&fm=jpg&crop=entropy&cs=tinysrgb&w=200&fit=max&ixid=eyJhcHBfaWQiOjEwOTk3Nn0"
            },
            "links": {
                "self": "https://api.unsplash.com/photos/Bm4IvGf2al0",
                "html": "https://unsplash.com/photos/Bm4IvGf2al0",
                "download": "https://unsplash.com/photos/Bm4IvGf2al0/download",
                "download_location": "https://api.unsplash.com/photos/Bm4IvGf2al0/download"
            },
            "categories": [],
            "likes": 27,
            "liked_by_user": false,
            "current_user_collections": [],
            "user": {
                "id": "5O8pXRavaLE",
                "updated_at": "2020-01-21T13:01:08-05:00",
                "username": "alexrvasey",
                "name": "Alex Vasey",
                "first_name": "Alex",
                "last_name": "Vasey",
                "twitter_username": "alexvasey",
                "portfolio_url": "https://www.instagram.com/alexrvasey/",
                "bio": "american in bruxelles. wanderer. pretend photographer. southpaw. go 'skers. digital comms.",
                "location": "Bruxelles, Belgique",
                "links": {
                    "self": "https://api.unsplash.com/users/alexrvasey",
                    "html": "https://unsplash.com/@alexrvasey",
                    "photos": "https://api.unsplash.com/users/alexrvasey/photos",
                    "likes": "https://api.unsplash.com/users/alexrvasey/likes",
                    "portfolio": "https://api.unsplash.com/users/alexrvasey/portfolio",
                    "following": "https://api.unsplash.com/users/alexrvasey/following",
                    "followers": "https://api.unsplash.com/users/alexrvasey/followers"
                },
                "profile_image": {
                    "small": "https://images.unsplash.com/profile-1490028258062-50ff05f6cbec?ixlib=rb-1.2.1&q=80&fm=jpg&crop=faces&cs=tinysrgb&fit=crop&h=32&w=32",
                    "medium": "https://images.unsplash.com/profile-1490028258062-50ff05f6cbec?ixlib=rb-1.2.1&q=80&fm=jpg&crop=faces&cs=tinysrgb&fit=crop&h=64&w=64",
                    "large": "https://images.unsplash.com/profile-1490028258062-50ff05f6cbec?ixlib=rb-1.2.1&q=80&fm=jpg&crop=faces&cs=tinysrgb&fit=crop&h=128&w=128"
                },
                "instagram_username": "alexrvasey",
                "total_collections": 13,
                "total_likes": 689,
                "total_photos": 147,
                "accepted_tos": true
            },
            "tags": [
                {
                    "type": "search",
                    "title": "building"
                },
                {
                    "type": "search",
                    "title": "architecture"
                },
                {
                    "type": "search",
                    "title": "tower"
                }
            ]
        }
    ]
}